license.txt
setup.py
afnan159.egg-info/PKG-INFO
afnan159.egg-info/SOURCES.txt
afnan159.egg-info/dependency_links.txt
afnan159.egg-info/top_level.txt
code/__init__.py