Metadata-Version: 2.1
Name: afnan159
Version: 0.1
Summary: library in python
Author: afnan salm
License-File: license.txt
